{
    "current_price": 40240.0,
    "predicted_price": 39860.55078125,
    "prediction_date": "2024-07-26",
    "prediction_days": 1,
    "mae": 1126.4203125,
    "trade_direction": "SHORT \ud83d\udcc9",
    "entry_price": 41007.0,
    "stop_loss": 42237.21,
    "target_price_1": 39860.55078125,
    "target_price_2": 40055.0,
    "highest_price_4d": 41007.0,
    "lowest_price_4d": 40055.0,
    "token": "MYM=F",
    "highest_volume_prices": [
        {
            "date": "2024-07-25 00:00",
            "price": 40240.0,
            "volume": 185168
        },
        {
            "date": "2024-07-18 00:00",
            "price": 40958.0,
            "volume": 150901
        },
        {
            "date": "2024-07-19 00:00",
            "price": 40562.0,
            "volume": 135945
        },
        {
            "date": "2024-07-22 00:00",
            "price": 40693.0,
            "volume": 104630
        }
    ],
    "price_1d_ago": 40208.0,
    "price_2d_ago": 40599.0,
    "price_3d_ago": 40714.0,
    "price_4d_ago": null
}